modelconv-0.4.5.dist-info/licenses/LICENSE
modelconverter/__init__.py
modelconverter/__main__.py
modelconverter/cli/__init__.py
modelconverter/cli/utils.py
modelconverter/hub/__init__.py
modelconverter/hub/__main__.py
modelconverter/hub/convert.py
modelconverter/hub/hub_requests.py
modelconverter/hub/typing.py
modelconverter/packages/__init__.py
modelconverter/packages/base_analyze.py
modelconverter/packages/base_benchmark.py
modelconverter/packages/base_exporter.py
modelconverter/packages/base_inferer.py
modelconverter/packages/base_visualize.py
modelconverter/packages/getters.py
modelconverter/packages/multistage_exporter.py
modelconverter/packages/hailo/__init__.py
modelconverter/packages/hailo/exporter.py
modelconverter/packages/hailo/inferer.py
modelconverter/packages/hailo/requirements.txt
modelconverter/packages/rvc2/__init__.py
modelconverter/packages/rvc2/benchmark.py
modelconverter/packages/rvc2/exporter.py
modelconverter/packages/rvc2/inferer.py
modelconverter/packages/rvc2/requirements.txt
modelconverter/packages/rvc3/__init__.py
modelconverter/packages/rvc3/benchmark.py
modelconverter/packages/rvc3/exporter.py
modelconverter/packages/rvc3/inferer.py
modelconverter/packages/rvc3/requirements.txt
modelconverter/packages/rvc4/__init__.py
modelconverter/packages/rvc4/analyze.py
modelconverter/packages/rvc4/benchmark.py
modelconverter/packages/rvc4/exporter.py
modelconverter/packages/rvc4/inferer.py
modelconverter/packages/rvc4/requirements.txt
modelconverter/packages/rvc4/visualize.py
modelconverter/utils/__init__.py
modelconverter/utils/adb_handler.py
modelconverter/utils/calibration_data.py
modelconverter/utils/config.py
modelconverter/utils/constants.py
modelconverter/utils/docker_utils.py
modelconverter/utils/environ.py
modelconverter/utils/exceptions.py
modelconverter/utils/filesystem_utils.py
modelconverter/utils/general.py
modelconverter/utils/hubai_utils.py
modelconverter/utils/image.py
modelconverter/utils/layout.py
modelconverter/utils/metadata.py
modelconverter/utils/nn_archive.py
modelconv-0.4.5.dist-info/METADATA
modelconv-0.4.5.dist-info/WHEEL
modelconv-0.4.5.dist-info/entry_points.txt
modelconv-0.4.5.dist-info/top_level.txt
modelconv-0.4.5.dist-info/RECORD
