Metadata-Version: 2.4
Name: modelconv
Version: 0.4.5
Summary: Converter for neural models into various formats.
Author-email: Luxonis <support@luxonis.com>
Maintainer-email: Luxonis <support@luxonis.com>
Project-URL: repository, https://github.com/luxonis/modelconverter
Project-URL: issues, https://github.com/luxonis/modelconverter/issues
Keywords: ml,onnx,openvino,nn,ai,embedded
Classifier: Development Status :: 4 - Beta
Classifier: Programming Language :: Python :: 3.10
Classifier: Topic :: Scientific/Engineering :: Artificial Intelligence
Classifier: Topic :: Scientific/Engineering :: Image Processing
Classifier: Topic :: Scientific/Engineering :: Image Recognition
Requires-Python: >=3.10
License-File: LICENSE
Requires-Dist: Pillow
Requires-Dist: gcsfs
Requires-Dist: luxonis-ml[data,nn_archive]==0.8.0
Requires-Dist: onnx<1.19.0,>=1.17.0
Requires-Dist: onnxruntime
Requires-Dist: onnxsim
Requires-Dist: s3fs
Requires-Dist: s3transfer
Requires-Dist: click==8.1.8
Requires-Dist: cyclopts
Requires-Dist: docker
Requires-Dist: keyring
Requires-Dist: onnx_graphsurgeon
Requires-Dist: onnxoptimizer
Requires-Dist: wget
Requires-Dist: aiobotocore<2.18
Requires-Dist: psutil
Provides-Extra: bench
Requires-Dist: depthai~=3.0.0; extra == "bench"
Provides-Extra: analysis
Requires-Dist: polars; extra == "analysis"
Requires-Dist: plotly; extra == "analysis"
Provides-Extra: dev
Requires-Dist: pre-commit==3.2.1; extra == "dev"
Requires-Dist: pytest-cov>=4.1.0; extra == "dev"
Requires-Dist: depthai~=3.0.0; extra == "dev"
Provides-Extra: rvc2
Requires-Dist: tflite2onnx; extra == "rvc2"
Requires-Dist: bsdiff4; extra == "rvc2"
Requires-Dist: pebble; extra == "rvc2"
Provides-Extra: rvc3
Requires-Dist: tflite2onnx; extra == "rvc3"
Provides-Extra: rvc4
Requires-Dist: tflite; extra == "rvc4"
Requires-Dist: psutil; extra == "rvc4"
Requires-Dist: numpy<2; extra == "rvc4"
Requires-Dist: polars; extra == "rvc4"
Requires-Dist: pytest; extra == "rvc4"
Provides-Extra: hailo
Requires-Dist: nvidia-dali-cuda120==1.49.0; extra == "hailo"
Requires-Dist: nvidia-dali-tf-plugin-cuda120==1.49.0; extra == "hailo"
Requires-Dist: protobuf==3.20.3; extra == "hailo"
Dynamic: license-file
